[{"author":[{"given":"Yanjun","family":"Qi"}],"container-title":"Ensemble Machine Learning","DOI":"10.1007/978-1-4419-9326-7_11","type":"chapter","id":"Qi_2012","citation-key":"Qi_2012","ISBN":"9781441993267","issued":{"date-parts":[[2012]]},"page":"307-323","publisher":"Springer New York","title":"Random Forest for Bioinformatics","URL":"http://dx.doi.org/10.1007/978-1-4419-9326-7_11","_graph":[{"type":"@biblatex/text","data":" @inbook{Qi_2012, title={Random Forest for Bioinformatics}, ISBN={9781441993267}, url={http://dx.doi.org/10.1007/978-1-4419-9326-7_11}, DOI={10.1007/978-1-4419-9326-7_11}, booktitle={Ensemble Machine Learning}, publisher={Springer New York}, author={Qi, Yanjun}, year={2012}, pages={307–323} }\n"},{"type":"@biblatex/entries+list"},{"type":"@csl/list+object"}]}]